<query xmlns="http://labkey.org/data/xml/query">
    <metadata>
        <tables xmlns="http://labkey.org/data/xml">
            <table tableName="quality_metrics_analyses_pivoted" tableDbType="TABLE">
                <tableTitle>Quality Metrics By Analysis</tableTitle>
                <columns>
                    <column columnName="analysis_id">
                        <isKeyField>true</isKeyField>
                    </column>
                </columns>
            </table>
        </tables>
    </metadata>
</query>
